{
  "name": "10 maseczek wielokrotnego użytku",
  "description": "<p style=\"text-align:justify\"> Oferujemy <b> paczkę 10 maseczek wielokrotnego użytku </b> w cenie <b>£12</b>.</p> ",
  "short_description": "12 funtów za zestaw 10 maseczek wielokrotnego użytku - pakowanych próżniowo!",
  "highlights": "[\"Zdobądź paczkę 10 maseczek wielokrotnego użytku\",\"Miękkie i wygodne elastyczne pętelki na uszy\",\"Pakowane próżniowo i szczelnie zamknięte\", \"Wygodne do noszenia lub wkładania do torby.\"]",
  "terms": "[\"Możliwość zakupu kilku sztuk.\",\"Voucher ważny do 30 grudnia 2020.\",\"Dostawa kosztuje dodatkowo \\u00a33,99 za każdy voucher.\",\"Dostawa nie obejmuje wybranych kodów pocztowych w <a href=\\\" \\/page\\/ni-delivery-restrictions.html\\\"target=\\\"_blank\\\" rel =\\\"nofollow\\\"> Irlandii Północnej <\\/a>.\",\"Dostawa do siedmiu dni roboczych po realizacji\",\"Proszę pamiętać, że nie są to środki ochrony indywidualnej, urządzenia medyczne i nie nadają się do użytku w publicznej służbie zdrowia i domach opieki.\",\"W zależności od dostępności.\"]",
  "productdisplay_row": "{}",
  "productdisplay_column": "{}",
  "business_id": "16529364",
  "business_image_url": "https://static.wowcher.co.uk/images/business/16529364/4009279-logo.png",
  "business_image_alt": "Bez tytułu-1",
  "total_bought": "3618",
  "price_text": "teraz"
}