{
  "name": "Zabawkowy pociąg wydmuchujący bańki ",
  "description": "<p style=\"text-align:justify\"><i>Ciuch, ciuch...</i> Zwolnij drogę dzisiejszej fantastycznej ofercie!</p> <p style=\"text-align:justify\"> Proponujemy ci <b>dziecięcy pociąg wydmuchujący bańki z muzyką i lampkami</b> za <b>£12</b>.</p> <h3>Sprawdź nasze powiązane oferty:</h3> <ul><li><a href=\"https://www.wowcher.co.uk/guides/remote-control-cars-toys\" target=\"_blank\"> Oferty zdalnie sterowanych aut i zabawek</a> </li> </ul> ",
  "short_description": "£12 za zabawkowy pociąg wydmuchujący bańki dla twojego dziecka!",
  "deal_position": "193200",
  "highlights": "[” <b> Zabawkowy pociąg: <\\ /b> Kup zabawkowy pociąg wydmuchujący bańki dla twojego dziecka.\",” <b> Kreatywność: <\\ /b> Idealny do ćwiczenia kreatywności i wyobraźni twojego szkraba.\",” <b> Bańki: <\\ /b> Oglądaj radość na twarzach dzieci, kiedy zobaczą jak pociąg wydmuchuje bańki.\",” <b> Zabawa: <\\ /b> Super fajna zabawka, dzięki której twoje dzieci będą się wspaniale bawić.\",” <b> LED: <\\ /b> Zawiera migające diody LED i muzykę.\",” <b> Prezent: <\\ /b> To piękny prezent dla małego fana kolejarstwa!\"]",
  "terms": "[\"Można kupić kilka sztuk.\",\"Voucher ważny do 1 stycznia 2021. \", \"Koszt dostawy to dodatkowe\\ u00a32.99 za voucher (dostawa w Wielkiej Brytanii).\", \"Sugerujemy założenie realizacji w ciągu 10 dni roboczych po zrealizowaniu vouchera.    Potrzebuje 3 x baterie AA (niezałączone do zestawu).\".\"Odpowiednie dla dzieci w wieku trzech lat i starszych.\",\"W zależności od dostępności.\"]",
  "productdisplay_row": "{}",
  "productdisplay_column": "{}",
  "business_id": "16533601",
  "business_image_url": "https://static.wowcher.co.uk/images/business/16533601/4026261-logo.png",
  "business_image_alt": "Fullfilled-by-wowcher",
  "total_bought": "989",
  "price_text": "now"
}