{
  "name": "Oferta de calendario de Adviento de bisutería",
  "description": "<p style=\"text-align:justify\"> ¿Quieres ir un paso más allá para alguien a quien quieres esta Navidad? </p> <p style=\"text-align:justify\">Te ofrecemos un <b> calendario de adviento de bisutería</b> por solo <b> 19,99 libras.</b> </p> <p style=\"text-align:justify\"> La Navidad es una vez al año, pero no tienes que esperar al 25 de diciembre para demostrar que te importa. Con este <b>calendario de adviento</b> de lujo, puedes sorprender a alguien especial cada día de diciembre. </p> <h3>Incluido</h3> <ul>Dentro de cada uno de los 24 bolsillos hay una fabulosa pieza de bisutería festiva: pulseras, pendientes, charms y mucho más. </ul> <h3>Hecho de diferentes metales</h3> <ul>Bisutería hecha de una gran variedad de metales, como aleaciones, latón, bañado en rodio y bañado en plata. Además, tres de los artículos incluidos están incluso hechos con cristales de Swarovski®. Y todo en un magnífico calendario de tela que se puede reutilizar año tras año.</ul> <h3>Diseños</h3> <ul><li>Reno</li> <li>Árbol</li> <li>Gorro de Santa</li></ul> <h3>Descubre nuestras ofertas relacionadas:</h3> <ul><li><a href=\"https://www.wowcher.co.uk/guides/beauty-advent-calendars\" target=\"_blank\"> Ofertas de calendario de adviento de belleza</a></li> <li><a href=\"https://www.wowcher.co.uk/guides/jewellery-advent-calendar\" target=\"_blank\"> Ofertas de calendario de adviento de bisutería</a></li> <li><a href=\"https://www.wowcher.co.uk/guides/stocking-filler-deals\" target=\"_blank\"> Ofertas de sorpresas navideñas</a></li></ul> ",
  "short_description": "Por 19,99 libras en lugar de 97 libras, tendrás un calendario de adviento de 24 días de bisutería con diseños de renos, árboles o sombreros de Santa Claus de Your Ideal Gift; ahorrarás un 79 %.",
  "deal_position": "1301500",
  "highlights": "[\"<b>Calendario de adviento:<\\/b> Regala a alguien especial un calendario de adviento de Navidad con bisutería.\",\"<b>Diseños:<\\/b> Disponibles diseños de calendarios de reno, árbol o sombrero de Santa Claus.\",\"<b>Incluye:</b> Bisutería para esconder en cada una de las 24 bolsas, como pulseras, pendientes, charms, etc.\",\"<b>Tres de los artículos incluidos están hechos con cristales de Swarovski \\u00ae.</b>\",\"<b>Reutilizable:</b> ¡El calendario se puede reutilizar año tras año!</b>\",\"<b>Regalo magnífico:</b> es un precioso regalo para una mujer especial.\"]",
  "terms": "[\"Se pueden comprar varios.\", \"Vale válido hasta el 12 de enero de 2021.\", \"La entrega cuesta 4,99 £ más por vale (entrega en el Reino Unido).\", \"La entrega puede tardar hasta cinco días laborables después de canjearlo.\", \"Sujeto a disponibilidad.\"]",
  "productdisplay_row": "{\"header\":\"your design:\",\"items\":[{\"id\":467132,\"header\":\"Reindeer\"},{\"id\":467133,\"header\":\"Tree\"},{\"id\":467134,\"header\":\"Santa hat\"}]}",
  "productdisplay_column": "{\"header\":\"-\",\"items\":[{\"id\":467135,\"header\":\"-\"}]}",
  "business_id": "16506639",
  "business_image_url": "https://static.wowcher.co.uk/images/business/16506639/3955700-logo.png",
  "business_image_alt": "your-ideal-gift-logo-final",
  "web_address": "http://www.youridealgift.co.uk/luxury-advent-calendar-2019?search=Calendar&description=true",
  "total_bought": "305",
  "price_text": "ahora"
}