{
  "name": "Kwiatowe klocki – zestaw zabawkowy   ",
  "description": "<p style=\"text-align:justify\">Wprowadź swoje dziecko w świat budowania korzystając z dzisiejszej wspaniałej oferty na zabawki…</p>\n<p style=\"text-align:justify\">Oferujemy <b>kwiatowy zestaw klocków</b> od zaledwie <b>£9,99</b> przez co oszczędzisz <b>do 67%</b> <a href=\" https://www.pinkpree.com/index.php/assembling-flower-building-block.html\"target=\"_blank\" rel =\"nofollow\">ceny PinkPree</a> (w dniu 3.09.2020).</p>\n",
  "short_description": "Od £9,99 zamiast £29,99 funta za zestaw klocków kwiatowych dla dzieci, do wyboru w trzech rozmiarach od PinkPree - oszczędzaj do 67%.",
  "deal_position": "6000",
  "highlights": "[\"<b>Klocki:<\\/b> Złóż swoje własne, jasne wysokie i piękne kwiaty za pomocą tego fantastycznego zestawu klocków.\",\"<b>Zawartość:<\\/b> Zawiera zielone łodygi z liśćmi z wieloma wspaniałymi kwiatami do umieszczenia na ich szczycie.\",\"<b>Umiejętności:<\\/b> Rozwija chwytność, precyzyjne zdolności motoryczne oraz zdolności rozwiązywania problemów u twojego dziecka, dodatkowo uczy kolorów i kreatywności.\",\"<b>Materiał:<\\/b> Wykonane z nietoksycznego plastiku bez BPA.\",\"<b>Odpowiednie dla:<\\/b> Dzieci w wieku trzech lat lub więcej.\",\"<b>Wielkości:<\\/b> Wybierz zestaw klocków z 54, 104 lub 171 elementów!\"]",
  "terms": "[\"Możliwość zakupu kilku sztuk.\",\"Voucher ważny do 11 stycznia 2021.   \",\"54-elementowy zestaw: Dostawa kosztuje dodatkowo \\u00a32,99 za voucher.\",\"Zestaw 104 i 171 elementów: Dostawa kosztuje dodatkowo \\u00a33,99 za voucher.\",\"Dostawa do 14 dni roboczych po realizacji.  \",\"W zależności od dostępności.   \"]",
  "productdisplay_row": "{\"header\":\"your size:\",\"items\":[{\"id\":464646,\"header\":\"54-PIECE SET\"},{\"id\":464647,\"header\":\"104-PIECE SET\"},{\"id\":464648,\"header\":\"171-PIECE SET\"}]}",
  "productdisplay_column": "{\"header\":\"-\",\"items\":[{\"id\":464649,\"header\":\"-\"}]}",
  "business_id": "16533558",
  "business_image_url": "https://static.wowcher.co.uk/images/business/16533558/4026113-logo.png",
  "business_image_alt": "pink-pree",
  "web_address": "https://www.pinkpree.com/index.php/assembling-flower-building-block.html",
  "total_bought": "24",
  "price_text": "od"
}